[
  {
    "chunk_id": "LAW_CHUNK_001_001",
    "doc_id": "DOC_001",
    "title": "Bộ luật Dân sự 2015",
    "so_ky_hieu": "91/2015/QH13",
    "loai_van_ban": "Bộ luật",
    "ngay_ban_hanh": "2015-11-24",
    "ngay_co_hieu_luc": "2017-01-01",
    "ngay_het_hieu_luc": null,
    "tinh_trang_hieu_luc": "Còn hiệu lực",
    "co_quan_ban_hanh": "Quốc hội",
    "linh_vuc": "Dân sự",
    "article": "Điều 434",
    "clause": null,
    "content": "Điều 434. Nghĩa vụ giao tài sản. Bên bán có nghĩa vụ giao tài sản cho bên mua đúng số lượng, chất lượng, chủng loại, thời hạn và địa điểm đã thỏa thuận.",
    "source": "vbpl.vn"
  },
  {
    "chunk_id": "LAW_CHUNK_001_002",
    "doc_id": "DOC_001",
    "title": "Bộ luật Dân sự 2015",
    "so_ky_hieu": "91/2015/QH13",
    "loai_van_ban": "Bộ luật",
    "ngay_ban_hanh": "2015-11-24",
    "ngay_co_hieu_luc": "2017-01-01",
    "ngay_het_hieu_luc": null,
    "tinh_trang_hieu_luc": "Còn hiệu lực",
    "co_quan_ban_hanh": "Quốc hội",
    "linh_vuc": "Dân sự",
    "article": "Điều 440",
    "clause": null,
    "content": "Điều 440. Nghĩa vụ thanh toán. Bên mua có nghĩa vụ thanh toán tiền theo thời hạn, địa điểm và mức tiền được thỏa thuận trong hợp đồng.",
    "source": "vbpl.vn"
  },
  {
    "chunk_id": "LAW_CHUNK_001_003",
    "doc_id": "DOC_001",
    "title": "Bộ luật Dân sự 2015",
    "so_ky_hieu": "91/2015/QH13",
    "loai_van_ban": "Bộ luật",
    "ngay_ban_hanh": "2015-11-24",
    "ngay_co_hieu_luc": "2017-01-01",
    "ngay_het_hieu_luc": null,
    "tinh_trang_hieu_luc": "Còn hiệu lực",
    "co_quan_ban_hanh": "Quốc hội",
    "linh_vuc": "Dân sự",
    "article": "Điều 351",
    "clause": null,
    "content": "Điều 351. Trách nhiệm do vi phạm nghĩa vụ. Trường hợp bên có nghĩa vụ vi phạm nghĩa vụ thì phải chịu trách nhiệm dân sự đối với bên có quyền.",
    "source": "vbpl.vn"
  },
  {
    "chunk_id": "LAW_CHUNK_001_004",
    "doc_id": "DOC_001",
    "title": "Bộ luật Dân sự 2015",
    "so_ky_hieu": "91/2015/QH13",
    "loai_van_ban": "Bộ luật",
    "ngay_ban_hanh": "2015-11-24",
    "ngay_co_hieu_luc": "2017-01-01",
    "ngay_het_hieu_luc": null,
    "tinh_trang_hieu_luc": "Còn hiệu lực",
    "co_quan_ban_hanh": "Quốc hội",
    "linh_vuc": "Dân sự",
    "article": "Điều 360",
    "clause": null,
    "content": "Điều 360. Trách nhiệm bồi thường thiệt hại do vi phạm nghĩa vụ. Trường hợp có thiệt hại do vi phạm nghĩa vụ gây ra thì bên vi phạm phải bồi thường toàn bộ thiệt hại.",
    "source": "vbpl.vn"
  },
  {
    "chunk_id": "LAW_CHUNK_002_001",
    "doc_id": "DOC_002",
    "title": "Luật Thương mại 2005",
    "so_ky_hieu": "36/2005/QH11",
    "loai_van_ban": "Luật",
    "ngay_ban_hanh": "2005-06-14",
    "ngay_co_hieu_luc": "2006-01-01",
    "ngay_het_hieu_luc": null,
    "tinh_trang_hieu_luc": "Còn hiệu lực",
    "co_quan_ban_hanh": "Quốc hội",
    "linh_vuc": "Thương mại",
    "article": "Điều 37",
    "clause": null,
    "content": "Điều 37. Thời hạn giao hàng. Bên bán phải giao hàng vào đúng thời điểm giao hàng đã thỏa thuận trong hợp đồng.",
    "source": "vbpl.vn"
  },
  {
    "chunk_id": "LAW_CHUNK_002_002",
    "doc_id": "DOC_002",
    "title": "Luật Thương mại 2005",
    "so_ky_hieu": "36/2005/QH11",
    "loai_van_ban": "Luật",
    "ngay_ban_hanh": "2005-06-14",
    "ngay_co_hieu_luc": "2006-01-01",
    "ngay_het_hieu_luc": null,
    "tinh_trang_hieu_luc": "Còn hiệu lực",
    "co_quan_ban_hanh": "Quốc hội",
    "linh_vuc": "Thương mại",
    "article": "Điều 50",
    "clause": null,
    "content": "Điều 50. Thanh toán. Bên mua có nghĩa vụ thanh toán tiền mua hàng và nhận hàng theo thỏa thuận.",
    "source": "vbpl.vn"
  }
]
